loq/__init__.py
loq/__main__.py
loq-0.1.0a7.data/scripts/loq
loq-0.1.0a7.dist-info/METADATA
loq-0.1.0a7.dist-info/WHEEL
loq-0.1.0a7.dist-info/licenses/LICENSE
loq-0.1.0a7.dist-info/RECORD
