Metadata-Version: 2.4
Name: loq
Version: 0.1.0a7
Classifier: Development Status :: 4 - Beta
Classifier: Environment :: Console
Classifier: Intended Audience :: Developers
Classifier: License :: OSI Approved :: MIT License
Classifier: Operating System :: OS Independent
Classifier: Programming Language :: Python :: 3
Classifier: Programming Language :: Python :: 3.8
Classifier: Programming Language :: Python :: 3.9
Classifier: Programming Language :: Python :: 3.10
Classifier: Programming Language :: Python :: 3.11
Classifier: Programming Language :: Python :: 3.12
Classifier: Programming Language :: Python :: 3.13
Classifier: Programming Language :: Rust
Classifier: Topic :: Software Development :: Quality Assurance
License-File: LICENSE
Summary: Enforce file size constraints
Keywords: linter,code-quality,file-size,loc,lines-of-code
Author-email: Jake Kaplan <jakegkaplan@gmail.com>
License: MIT
Requires-Python: >=3.8
Project-URL: Repository, https://github.com/jakekaplan/loq
